pinax/__init__.py
pinax/documents/__init__.py
pinax/documents/apps.py
pinax/documents/compat.py
pinax/documents/conf.py
pinax/documents/exceptions.py
pinax/documents/forms.py
pinax/documents/hooks.py
pinax/documents/managers.py
pinax/documents/models.py
pinax/documents/receivers.py
pinax/documents/urls.py
pinax/documents/utils.py
pinax/documents/views.py
pinax/documents/migrations/0001_initial.py
pinax/documents/migrations/0002_auto_20161230_1051.py
pinax/documents/migrations/0003_populate_original_filename.py
pinax/documents/migrations/0004_auto_20161230_1057.py
pinax/documents/migrations/__init__.py
pinax/documents/templatetags/__init__.py
pinax/documents/templatetags/pinax_documents_tags.py
pinax/documents/tests/__init__.py
pinax/documents/tests/test.py
pinax/documents/tests/test_views.py
pinax/documents/tests/urls.py
pinax_documents-2.0.0.dist-info/AUTHORS
pinax_documents-2.0.0.dist-info/LICENSE
pinax_documents-2.0.0.dist-info/METADATA
pinax_documents-2.0.0.dist-info/WHEEL
pinax_documents-2.0.0.dist-info/top_level.txt
pinax_documents-2.0.0.dist-info/RECORD
